__init__.py
import_only_py.py
setup.py
import_only_py.egg-info/PKG-INFO
import_only_py.egg-info/SOURCES.txt
import_only_py.egg-info/dependency_links.txt
import_only_py.egg-info/top_level.txt